<?xml version="1.0" encoding="UTF-8"?>
<beans xmlns="http://www.springframework.org/schema/beans"
    xmlns:xsi="http://www.w3.org/2001/XMLSchema-instance"
    xmlns:p="http://www.springframework.org/schema/p"
    xsi:schemaLocation="http://www.springframework.org/schema/beans
    https://www.springframework.org/schema/beans/spring-beans.xsd">
    
     <bean id="adr" class="com.cjc.Address">
     <property name="cityname" value="pune"></property>
   <property name="areaname" value="karvenagar"></property>
   </bean>
   <bean id="stu" class="com.cjc.Student">
     <property name="rollno" value="1"></property>
   <property name="name" value="parag"></property>
    <property name="addr" ref="adr"></property>
     </bean>
     
      </beans>